MANIFEST.in
README.md
README.rst
setup.py
mimo/__init__.py
mimo/test_helper.py
mimo.egg-info/PKG-INFO
mimo.egg-info/SOURCES.txt
mimo.egg-info/dependency_links.txt
mimo.egg-info/requires.txt
mimo.egg-info/top_level.txt
mimo/asynctools/__init__.py
mimo/asynctools/range.py
mimo/asynctools/zip.py
mimo/io/__init__.py
mimo/io/input.py
mimo/io/io_set.py
mimo/io/output.py
mimo/stream/__init__.py
mimo/stream/stream.py
mimo/stream/stream_from_input.py
mimo/stream/stream_from_iterator.py
mimo/stream/stream_from_list.py
mimo/stream/stream_to_list.py
mimo/stream/stream_to_output.py
mimo/workflow/__init__.py
mimo/workflow/node.py
mimo/workflow/workflow.py
tests/test_connection/__init__.py
tests/test_connection/test_input.py
tests/test_stream/__init__.py
tests/test_stream/test_stream.py
tests/test_workflow/__init__.py
tests/test_workflow/test_node.py
tests/test_workflow/test_workflow.py