Metadata-Version: 1.1
Name: mimo
Version: 1.2.3
Summary: A streaming multi-input, multi-output Python library
Home-page: https://github.com/childsish/mimo
Author: Liam H. Childs
Author-email: liam.h.childs@gmail.com
License: LICENSE.txt
Platform: UNKNOWN
Classifier: Development Status :: 5 - Production/Stable
Classifier: Intended Audience :: Science/Research
Classifier: Topic :: Scientific/Engineering :: Bio-Informatics
